Workbook

Sheet NBCS Financial Report
A4: Reference: | C4: Nebraska Accounting Code Manual for Counties | D4: at the following web link:
D5: http://auditors.nebraska.gov/County_Info/County_Manual.html
C6: For Codes listed below, refer to Chapter 4 (Revenue) and Chapter 5 (Expenditures)
A8: Municipality or County: | D8: Fiscal Year Ending:
A10: Item No. | B10: Item | D10: Estimated for this Fiscal Year | E10: Actual for this Fiscal Year | F10: Estimates for Next Fiscal Year
A12: CASH BALANCE | C12: BEGINNING CASH BALANCE | E12: =+D12 -> 0
A13: For this Fiscal Year, if Actual was not equal to Estimated, explain:
A15: 301-329, 350-359, 398-540, 590, and Township Sources | C15: LOCAL REVENUE SOURCES (COUNTY & MUNICIPALITY) | D15: =+'Revenu Data'!D41 -> 0 | E15: =+'Revenu Data'!E41 -> 0 | F15: =+'Revenu Data'!F41 -> 0
A16: 301-309 | C16: Property Tax
A17: 310 | C17: Inheritance Tax
A18: 311-313 | C18: Local Sales Tax
A19: 314-315 | C19: 911 Tax and Lodging Tax
A20: 316.01 | C20: Wheel Tax
A21: 317 | C21: Special Assessments (county) | G21: What's the difference with 490.02? Are these just special assessments by counties?
A22: 318 | C22: Occupation Tax
A23: 320-329 | C23: License and Permit revenues
A24: 398-540 | C24: MISCELLANEOUS REVENUE
A25: 490-491 | C25: Special Assessment - Paving (cities, villages) | G25: What's the difference with 317?
A26: 510 | C26: Interest on Investments
A27: 520.01 | C27: Proceeds from the Sale of Bonds
A28: 520.02 | C28: Registered Warrants/Loans
A29: 530 | C29: Sale of Property, Supplies, Materials
A30: 534.01 | C30: Donations (money only)
C31: Any Other Miscellaneous Revenue
A32: 350-359 | C32: INTERGOVERNMENTAL REVENUE
A33: 351.04 | C33: Interlocal Government Payments - Roads
A34: 353.02 | C34: In Lieu of Taxes - 5% Gross Revenue
C35: Any Other Intergovenmental Revenue
A36: 590 | C36: COUNTY TRANSFERS
A37: 590.01 | C37: Transfers - Local Matching Funds
A38: 590.02 | C38: Transfers - Inter-fund
A39: 590.03 | C39: Transfers - Sinking Funds
A40: 590.04 | C40: Transfers - Closed funds
C41: Any Other Transfers (Specify)
C42: TOWNSHIP SOURCES (Specify)
C45: TOTAL FROM LOCAL SOURCES | D45: =SUM(D16:D44) -> 0 | E45: =SUM(E16:E44) -> 0 | F45: =SUM(F16:F44) -> 0
A46: 340-349 | C46: STATE REVENUE SOURCES | D46: =+'Revenu Data'!D63 -> 0 | E46: =+'Revenu Data'!E63 -> 0.01 | F46: =+'Revenu Data'!F63 -> 0
A47: 340.20 | C47: State Natural Disaster | G47: ??? | H47: is this state-aid emergency flooding relief?
A48: 344.01 | C48: Homestead Exemption Allocation
A49: 344.05 | C49: Property Tax Credit
A50: 345.05 | C50: Property Tax Relief
A51: 345.06 | C51: Property Tax Reimbursement
A52: 346.01 | C52: Pro-Rata Motor Vehicle Allocation
A53: 346.03 | C53: Motor Vehicle Fee (Road)
A54: 346.04 | C54: County Sales Tax
A55: 347.01 | C55: Highway/Street Allocation
A56: 347.02 | C56: Incentive Payments
A57: 347.04 | C57: Motor Vehicle Sales Tax
A58: 347.05 | C58: Municipality Relinquished Funds
A59: 347.50 | C59: Highway/Street Buyback Program (STP)
A60: 347.60 | C60: Highway Bridge Buyback Program (HBP)
C61: All Other STATE Sources (Specify)
G62: What happened to Make Up Funds 347.03?
C64: TOTAL FROM STATE SOURCES | D64: =SUM(D47:D63) -> 0 | E64: =SUM(E47:E63) -> 0 | F64: =SUM(F47:F63) -> 0
A65: 330-339 | C65: FEDERAL REVENUE SOURCES | D65: =+'Revenu Data'!D73 -> 0 | E65: =+'Revenu Data'!E73 -> 0 | F65: =+'Revenu Data'!F73 -> 0
A66: 330-333 | C66: STP, BR, BRO, HSIP, TAP, RRZ, CMAQ
A67: 334 | C67: Emergency Flood Relief (ER)
A68: 335 | C68: Forest Reserve
A69: 336-339 | C69: Other Federal Grants including CDBG
C70: All Other FEDERAL Sources (Specify)
C73: TOTAL FROM FEDERAL SOURCES | D73: =SUM(D66:D72) -> 0 | E73: =SUM(E66:E72) -> 0 | F73: =SUM(F66:F72) -> 0
C74: TOTAL REVENUE  | D74: =+D12+D15+D46+D65 -> 0 | E74: =+E12+E15+E46+E65 -> 0.01 | F74: =+F12+F15+F46+F65 -> 0
C76: EXPENDITURES FROM NBCS FORM 1 | D76: =+#REF! -> #REF! | E76: =+#REF! -> #REF! | F76: =+#REF! -> #REF!
C77: EXPENDITURES
A78: 1 | C78: PERSONAL SERVICES | D78: =+'Expend Data'!D28 -> 0 | E78: =+'Expend Data'!E28 -> 0 | F78: =+'Expend Data'!F28 -> 0
A79: 2 | C79: OPERATING EXPENSES | D79: =+'Expend Data'!D85 -> 0 | E79: =+'Expend Data'!E85 -> 0 | F79: =+'Expend Data'!F85 -> 0
A80: 3 | C80: SUPPLIES AND MATERIALS | D80: =+'Expend Data'!D133 -> 0 | E80: =+'Expend Data'!E133 -> 0 | F80: =+'Expend Data'!F133 -> 0
A81: 4 | C81: EQUIPMENT RENTAL | D81: =+'Expend Data'!D145 -> 0 | E81: =+'Expend Data'!E145 -> 0 | F81: =+'Expend Data'!F145 -> 0
A82: 5 | C82: CAPITAL OUTLAYS | D82: =+'Expend Data'!D206 -> 0 | E82: =+'Expend Data'!E206 -> 0 | F82: =+'Expend Data'!F206 -> 0
A83: 6 | C83: DEBT SERVICING | D83: =+'Expend Data'!D216 -> 0 | E83: =+'Expend Data'!E216 -> 0 | F83: =+'Expend Data'!F216 -> 0
A84: 7 | C84: TRANSFERS | D84: =+'Expend Data'!D222 -> 0 | E84: =+'Expend Data'!E222 -> 0 | F84: =+'Expend Data'!F222 -> 0
A85: Counties Only: | C85: ALL TOWNSHIPS EXPENDITURES ON ROADS | D85: =+'Expend Data'!D224 -> 0 | E85: =+'Expend Data'!E224 -> 0 | F85: =+'Expend Data'!F224 -> 0
C86: TOTAL EXPENDITURES  | D86: =SUM(D78:D85) -> 0 | E86: =SUM(E78:E85) -> 0 | F86: =SUM(F78:F85) -> 0
A89: CASH BALANCE | C89: ENDING CASH BALANCE | D89: =+D74-D86 -> 0 | E89: =+E74-E86 -> 0.01 | F89: =+F74-F86 -> 0
A91: INDIRECT BENEFITS | C91: STATE | D91: =+'Revenu Data'!D81 -> 0 | E91: =+'Revenu Data'!E81 -> 0 | F91: =+'Revenu Data'!F81 -> 0
C92: FEDERAL | D92: =+'Revenu Data'!D82 -> 0 | E92: =+'Revenu Data'!E82 -> 0 | F92: =+'Revenu Data'!F82 -> 0
C93: OTHER monetary value of donations such as land, equipment and labor (attach description), roads/streets constructed by developers, contributions from other sources such as schools and hospitals, and any other indirect sources | D93: =+'Revenu Data'!D83 -> 0 | E93: =+'Revenu Data'!E83 -> 0 | F93: =+'Revenu Data'!F83 -> 0
C94: TOTAL INDIRECT BENEFITS | D94: =SUM(D91:D93) -> 0 | E94: =SUM(E91:E93) -> 0 | F94: =SUM(F91:F93) -> 0
A96: Minimum Required Matching Funds per Neb. Rev. Stat. Chapter 39 Article 25 Distribution to Political Subdivisions
A98: =+'Revenu Data'!E52 -> 0.01 | C98: = Highway Allocation Funds (HAF) received this fiscal year, and required by State law to be matched, in $
A100: =0.25*D101 -> 0 | C100: = Percentage of HAF required to be matched (based on a full fiscal-year's allocation)
D101: 0
A104: =+A98*A100 -> 0 | C104: = Minimum amount of matching funds ($) required by State law
A106: 0 | C106: = Matching funds ($) provided this Fiscal Year, in dollars | E106: =+E86-#REF! -> #REF!
C107: Note: borrowed funds (e.g. bond, bank loan, etc.) may be spread equally over the term.
A109: =+A106/A98 -> 0 | C109: = Matching Funds percentage provided this fiscal year (Matching Funds ÷ HAF Received)
E112: Motion to accept this report was approved at a meeting of the governing body on this date:
A115: Printed Name of Chairman of County Board/Mayor/President/Chief Executive Officer/City Council | D115: Printed Name of County Highway or City Street Superintendent
A119: Signature Chairman of County Board/Mayor/President/Chief Executive Officer/City Council | D119: Signature of County Highway or City Street Superintendent

Sheet Revenu Data
A2: ROADS & STREETS FINANCIAL REPORT
A3: TO
A4: BOARD OF PUBLIC ROADS CLASSIFICATIONS AND STANDARDS
C6: Reference Chapter 4 of the | D6: Nebraska Accounting Code Manual for Counties | H6: County Accounting Manual | M6: County Accounting Manual
H7: Numerical Revenue Codes found on pages: | M7: Citations and Definitions on these pages:
A8: Municipality or County: | B8: =+'NBCS Financial Report'!B8:C8 -> 0 | D8: Fiscal Year Ending: | E8: =+'NBCS Financial Report'!E8 -> 0 | H8: Combined File Page x/78 | I8: Chapter | J8: Section | K8: Page | M8: Combined File Page x/78 | N8: Chapter | O8: Section | P8: Page
C9: BEGINNING CASH BALANCE
A10: Item No. | B10: Item | D10: Estimated Fiscal Year | E10: Actual Fiscal Year | F10: Next Fiscal Year Estimates
C11: LOCAL SOURCES (COUNTY & MUNICIPALITY)
A12: 301-309 | C12: Property Tax | H12: 32 | I12: 4 | J12: A | K12: 1 | M12: 44 | N12: 4 | O12: B | P12: 1
A13: 310 | C13: Inheritance Tax | H13: 32 | I13: 4 | J13: A | K13: 1 | M13: 44 | N13: 4 | O13: B | P13: 1
A14: 311-313 | C14: Local Sales Tax | H14: 32 | I14: 4 | J14: A | K14: 1 | M14: 44 | N14: 4 | O14: B | P14: 1
A15: 314-315 | C15: 911 Tax and Lodging Tax | H15: 32 | I15: 4 | J15: A | K15: 1 | M15: 44 | N15: 4 | O15: B | P15: 1
A16: 316.01 | C16: Wheel Tax | H16: 32 | I16: 4 | J16: A | K16: 1 | M16: 44 | N16: 4 | O16: B | P16: 1
A17: 317 | C17: Special Assessments (county) | H17: 32 | I17: 4 | J17: A | K17: 1 | M17: 44 | N17: 4 | O17: B | P17: 1
A18: 318 | C18: Occupation Tax | H18: 33 | I18: 4 | J18: A | K18: 2 | M18: 44 | N18: 4 | O18: B | P18: 1
A19: 320-329 | C19: License and Permit revenues | H19: 33 | I19: 4 | J19: A | K19: 2 | M19: 45 | N19: 4 | O19: B | P19: 2-3
A20: 398-579 | C20: MISCELLANEOUS REVENUE
A21: 490-491 | C21: Special Assessment - Paving (cities, villages) | H21: 41 | I21: 4 | J21: A | K21: 10 | M21: 55 | N21: 4 | O21: B | P21: 12
A22: 510 | C22: Interest on Investments | H22: 42 | I22: 4 | J22: A | K22: 11 | M22: 56 | N22: 4 | O22: B | P22: 13
A23: 520.01 | C23: Proceeds from the Sale of Bonds | H23: 42 | I23: 4 | J23: A | K23: 11 | M23: 56 | N23: 4 | O23: B | P23: 13
A24: 520.02 | C24: Registered Warrants/Loans | H24: 42 | I24: 4 | J24: A | K24: 11 | M24: 56 | N24: 4 | O24: B | P24: 13
A25: 530 | C25: Sale of Property, Supplies, Materials | H25: 42 | I25: 4 | J25: A | K25: 11 | M25: 56 | N25: 4 | O25: B | P25: 13
A26: 534.01 | C26: Donations (money only) | H26: 42 | I26: 4 | J26: A | K26: 11 | M26: 57 | N26: 4 | O26: B | P26: 14
C27: Any Other Miscellaneous Revenue
A28: 350-359 | C28: INTERGOVERNMENTAL REVENUE | H28: 36 | I28: 4 | J28: A | K28: 5
A29: 351.04 | C29: Interlocal Government Payments - Roads | H29: 36 | I29: 4 | J29: A | K29: 5
A30: 353.02 | C30: In Lieu of Taxes - 5% Gross Revenue | H30: 36 | I30: 4 | J30: A | K30: 5 | M30: 49 | N30: 4 | O30: B | P30: 6
C31: Any Other Intergovenmental Revenue
A32: 590 | C32: COUNTY TRANSFERS | H32: 43 | I32: 4 | J32: A | K32: 12
A33: 590.01 | C33: Transfers - Local Matching Funds | H33: 43 | I33: 4 | J33: A | K33: 12 | M33: 57 | N33: 4 | O33: B | P33: 14
A34: 590.02 | C34: Transfers - Inter-fund | H34: 43 | I34: 4 | J34: A | K34: 12 | M34: 57 | N34: 4 | O34: B | P34: 14
A35: 590.03 | C35: Transfers - Sinking Funds | H35: 43 | I35: 4 | J35: A | K35: 12
A36: 590.04 | C36: Transfers - Closed funds | H36: 43 | I36: 4 | J36: A | K36: 12
C37: Any Other Transfers
C38: ALL TOWNSHIPS REVENUES FOR ROADS
C41: TOTAL REVENUES FROM LOCAL SOURCES | D41: =SUM(D12:D40) -> 0 | E41: =SUM(E12:E40) -> 0 | F41: =SUM(F12:F40) -> 0
A43: 340-349 | C43: STATE REVENUE SOURCES
A44: 340.20 | C44: State Natural Disaster | H44: 35 | I44: 4 | J44: A | K44: 4
A45: 344.01 | C45: Homestead Exemption Allocation | H45: 36 | I45: 4 | J45: A | K45: 5 | M45: 48 | N45: 4 | O45: B | P45: 5
A46: 344.05 | C46: Property Tax Credit | H46: 36 | I46: 4 | J46: A | K46: 5
A47: 345.05 | C47: Property Tax Relief | H47: 36 | I47: 4 | J47: A | K47: 5
A48: 345.06 | C48: Property Tax Reimbursement | H48: 36 | I48: 4 | J48: A | K48: 5
A49: 346.01 | C49: Pro-Rata Motor Vehicle Allocation | H49: 36 | I49: 4 | J49: A | K49: 5 | M49: 48 | N49: 4 | O49: B | P49: 5
A50: 346.03 | C50: Motor Vehicle Fee (Road) | H50: 36 | I50: 4 | J50: A | K50: 5
A51: 346.04 | C51: County Sales Tax | H51: 36 | I51: 4 | J51: A | K51: 5
A52: 347.01 | C52: Highway/Street Allocation | E52: 0.01 | H52: 36 | I52: 4 | J52: A | K52: 5 | M52: 48 | N52: 4 | O52: B | P52: 5
A53: 347.02 | C53: Incentive Payments | H53: 36 | I53: 4 | J53: A | K53: 5 | M53: 48 | N53: 4 | O53: B | P53: 5
A54: 347.04 | C54: Motor Vehicle Sales Tax | H54: 36 | I54: 4 | J54: A | K54: 5
A55: 347.05 | C55: Municipality Relinquished Funds | H55: 36 | I55: 4 | J55: A | K55: 5 | M55: 48 | N55: 4 | O55: B | P55: 5
A56: 347.10 | C56: Road/Bridge Project Costs | H56: 36 | I56: 4 | J56: A | K56: 5
A57: 347.50 | C57: Highway/Street Buyback Program (STP) | H57: 36 | I57: 4 | J57: A | K57: 5
A58: 347.60 | C58: Highway Bridge Buyback Program (HBP) | H58: 36 | I58: 4 | J58: A | K58: 5
C62: All Other STATE Sources
C63: TOTAL FROM STATE SOURCES | D63: =SUM(D44:D62) -> 0 | E63: =SUM(E44:E62) -> 0.01 | F63: =SUM(F44:F62) -> 0
A65: 330-339 | C65: FEDERAL REVENUE SOURCES
A66: 330.38 | C66: Highway Safety | H66: 34 | I66: 4 | J66: A | K66: 3
A67: 330.5 | C67: Department of Roads | H67: 34 | I67: 4 | J67: A | K67: 3 | M67: 46 | N67: 4 | O67: B | P67: 3
A68: 334.01 | C68: Emergency Flood Relief | H68: 35 | I68: 4 | J68: A | K68: 4 | M68: 47 | N68: 4 | O68: B | P68: 4
A69: 336-339 | C69: Other Federal Grants including CDBG | H69: 35 | I69: 4 | J69: A | K69: 4 | M69: 47 | N69: 4 | O69: B | P69: 4
C72: All Other FEDERAL Sources
C73: TOTAL FROM FEDERAL SOURCES | D73: =SUM(D66:D72) -> 0 | E73: =SUM(E66:E72) -> 0 | F73: =SUM(F66:F72) -> 0
C74: TOTAL REVENUE  | D74: =+D41+D63+D73 -> 0 | E74: =+E41+E63+E73 -> 0.01 | F74: =+F41+F63+F73 -> 0
C76: EXPENDITURES FROM NBCS FORM 1 | D76: =+'Expend Data'!D226 -> 0 | E76: =+'Expend Data'!E226 -> 0 | F76: =+'Expend Data'!F226 -> 0
C78: ENDING CASH BALANCE
A81: INDIRECT BENEFITS not included in budget | C81: STATE
C82: FEDERAL
C83: OTHER monetary value of donations such as land, equipment and labor (attach description), roads/streets constructed by developers, contributions from other sources such as schools and hospitals, and any other indirect sources

Sheet Expend Data
A1: Municipality or County: | B1: =+'NBCS Financial Report'!B8:C8 -> 0 | D1: Fiscal Year Ending: | E1: =+'NBCS Financial Report'!E8 -> 0 | H1: County Accounting Manual Numerical Expenditure Codes | M1: County Accounting Manual Citations and Definitions
A2: Item No. | B2: Item | D2: Budget Fiscal Year | E2: Actual Expended Fiscal Year | F2: Budget Next Year | H2: Combined File Page x/78 | I2: Chapter | J2: Section | K2: Page | M2: Combined File Page x/78 | N2: Chapter | O2: Section | P2: Page
A3: PERSONAL SERVICES - 1 | M3: 74 | N3: 6 | O3: C | P3: 1
A4: 0300 - 0700 | C4: SALARIES - REGULAR & PART-TIME EMPLOYEES | H4: 62 | I4: 5 | J4: B | K4: 1 | M4: 74 | N4: 6 | O4: C | P4: 1
C5: INCLUDING OVERTIME, SPECIAL OVERTIME, HOLIDAY, BACK, VACATION AND SICK PAY | H5: 62 | I5: 5 | J5: B | K5: 1
B6: 0301/0401 | C6: Administrative | H6: 62 | I6: 5 | J6: B | K6: 1
C7: Engineering
B8: 0303/0403 | C8: Maintenance | H8: 62 | I8: 5 | J8: B | K8: 1
B9: 0304/0404 | C9: Construction | H9: 62 | I9: 5 | J9: B | K9: 1
B10: 0305/0405 | C10: Clerical | H10: 62 | I10: 5 | J10: B | K10: 1
B11: 0306/0406 | C11: Custodial | H11: 62 | I11: 5 | J11: B | K11: 1
C12: Other Salaries Not Reported Above
A13: 0800 | C13: INSURANCE PREMIUMS | H13: 63 | I13: 5 | J13: B | K13: 2 | M13: 74 | N13: 6 | O13: C | P13: 1
B14: 0801 | C14: Workmans Compensation | H14: 63 | I14: 5 | J14: B | K14: 2
B15: 0802 | C15: Health & Accident | H15: 63 | I15: 5 | J15: B | K15: 2
B16: 0803 | C16: Group | H16: 63 | I16: 5 | J16: B | K16: 2
B17: 0804 | C17: Life | H17: 63 | I17: 5 | J17: B | K17: 2
C18: Other insurance premiums
A19: 0900 | C19: RETIREMENT CONTRIBUTIONS | H19: 63 | I19: 5 | J19: B | K19: 2 | M19: 74 | N19: 6 | O19: C | P19: 1
A20: 1000 | C20: FICA - COUNTY (or MUNICIPALITY) SHARE | H20: 63 | I20: 5 | J20: B | K20: 2 | M20: 74 | N20: 6 | O20: C | P20: 1
A21: 1100 | C21: UNIFORM ALLOWANCE | H21: 63 | I21: 5 | J21: B | K21: 2 | M21: 74 | N21: 6 | O21: C | P21: 1
A22: 1200 | C22: INSURANCE ALLOWANCE | H22: 63 | I22: 5 | J22: B | K22: 2
A23: 1300 | C23: OTHER PERSONAL SERVICES | H23: 63 | I23: 5 | J23: B | K23: 2 | M23: 74 | N23: 6 | O23: C | P23: 1
A24: 1400 | C24: MISCELLANEOUS PERSONAL SERVICES | H24: 63 | I24: 5 | J24: B | K24: 2 | M24: 75 | N24: 6 | O24: C | P24: 2
A25: 1500 | C25: UNEMPLOYMENT CONTRIBUTIONS | H25: 63 | I25: 5 | J25: B | K25: 2 | M25: 75 | N25: 6 | O25: C | P25: 2
A26: 1600 | C26: COBRA REFUND | H26: 63 | I26: 5 | J26: B | K26: 2
C27: Other Personal Services not reported above
C28: PERSONAL SERVICES - 1 SUB-TOTAL: | D28: =SUM(D6:D27) -> 0 | E28: =SUM(E6:E27) -> 0 | F28: =SUM(F6:F27) -> 0
A29: OPERATING EXPENSES - 2 | M29: 75 | N29: 6 | O29: C | P29: 2
A30: 0100 | C30: POSTAL SERVICES | H30: 63 | I30: 5 | J30: B | K30: 2 | M30: 75 | N30: 6 | O30: C | P30: 2
A31: 0200 | C31: TELEPHONE SERVICES | H31: 63 | I31: 5 | J31: B | K31: 2 | M31: 75 | N31: 6 | O31: C | P31: 2
A32: 0400 | C32: RENTAL EXPENSES | H32: 63 | I32: 5 | J32: B | K32: 2
A33: 0500 | C33: UTILITIES | H33: 64 | I33: 5 | J33: B | K33: 3 | M33: 75 | N33: 6 | O33: C | P33: 2
B34: 0501 | C34: Light (Electricity) | H34: 64 | I34: 5 | J34: B | K34: 3
B35: 0502 | C35: Water | H35: 64 | I35: 5 | J35: B | K35: 3
B36: 0503 | C36: Heating Fuels | H36: 64 | I36: 5 | J36: B | K36: 3
B37: 0504 | C37: Sewer | H37: 64 | I37: 5 | J37: B | K37: 3
B38: 0505 | C38: Garbage | H38: 64 | I38: 5 | J38: B | K38: 3
C39: Other Utilities
A40: 0600 | C40: INSURANCE PREMIUMS | M40: 75 | N40: 6 | O40: C | P40: 2
B41: 0601 | C41: General Liability | H41: 64 | I41: 5 | J41: B | K41: 3
B42: 0616 | C42: Offical and Employee Bonds | H42: 64 | I42: 5 | J42: B | K42: 3
C43: Other Insurance Premiums
A44: 1000 | C44: GENERAL FINANCE/ADMINISTRATIVE EXPENSES | H44: 64 | I44: 5 | J44: B | K44: 3 | M44: 75 | N44: 6 | O44: C | P44: 2
B45: 1100 | C45: Data Processing Costs | H45: 64 | I45: 5 | J45: B | K45: 3
C46: Other General Finance/Administrative Expenses
A47: 1200 | C47: MAINTENANCE AND REPAIRS | H47: 65 | I47: 5 | J47: B | K47: 4 | M47: 75 | N47: 6 | O47: C | P47: 2
B48: 1210 | C48: Office Equipment Repair | H48: 65 | I48: 5 | J48: B | K48: 4
B49: 1305 | C49: Road Building Repair | H49: 65 | I49: 5 | J49: B | K49: 4
B50: 1400 | C50: Road Equipment Repair (other than labor) | H50: 65 | I50: 5 | J50: B | K50: 4
B51: 1500 | C51: Road Equipment Repair - Labor | H51: 65 | I51: 5 | J51: B | K51: 4
B52: 1550 | C52: Radio Equipment Repair | H52: 65 | I52: 5 | J52: B | K52: 4
C53: Other Maintenance and Repairs
A54: 1700 | C54: TRAVEL EXPENSES | H54: 65 | I54: 5 | J54: B | K54: 4 | M54: 75 | N54: 6 | O54: C | P54: 2
B55: 1701 | C55: Meals | H55: 65 | I55: 5 | J55: B | K55: 4
B56: 1702 | C56: Lodging | H56: 65 | I56: 5 | J56: B | K56: 4
B57: 1703 | C57: Transportation - Commerical | H57: 65 | I57: 5 | J57: B | K57: 4
C58: Other Travel Expenses
A59: 1750 | C59: TRAINING | H59: 65 | I59: 5 | J59: B | K59: 4 | M59: 75 | N59: 6 | O59: C | P59: 2
B60: 1751 | C60: Dues, Subscriptions, Registrations, Training, Fees | H60: 65 | I60: 5 | J60: B | K60: 4
B61: 1752 | C61: Convention/Workshop Expense | H61: 65 | I61: 5 | J61: B | K61: 4
B62: 1753 | C62: National Association Dues | H62: 65 | I62: 5 | J62: B | K62: 4
C63: Other Training Expenses
A64: 2500 | C64: CONTRACTUAL SERVICES | H64: 67 | I64: 5 | J64: B | K64: 6 | M64: 76 | N64: 6 | O64: C | P64: 3
B65: 2501 | C65: Consulting Fees | H65: 67 | I65: 5 | J65: B | K65: 6
B66: 2502 | C66: Professional Fees | H66: 67 | I66: 5 | J66: B | K66: 6
B67: 2530 | C67: Surveyor, Contracted Services | H67: 67 | I67: 5 | J67: B | K67: 6
B68: 2533 | C68: Engineering Costs | H68: 67 | I68: 5 | J68: B | K68: 6
B69: 2560 | C69: Road Maintenance - By Others | H69: 67 | I69: 5 | J69: B | K69: 6
B70: 2561 | C70: Snow Removal - By Others | H70: 67 | I70: 5 | J70: B | K70: 6
C73: Other Contractual Services
A74: 2601 | C74: FEMA GRANT COSTS | H74: 67 | I74: 5 | J74: B | K74: 6
A75: 4400 | C75: INTERGOVERNMENTAL PAYMENTS | H75: 68 | I75: 5 | J75: B | K75: 7 | M75: 76 | N75: 6 | O75: C | P75: 3
B76: 4405 | C76: Planning Costs | H76: 68 | I76: 5 | J76: B | K76: 7
B77: 4416 | C77: Road Improvements | H77: 68 | I77: 5 | J77: B | K77: 7
C78: Other Intergovernmental Payments
A79: 7000 | C79: JUDGMENTS - SETTLEMENTS | H79: 69 | I79: 5 | J79: B | K79: 8 | M79: 76 | N79: 6 | O79: C | P79: 3
A80: 9000 | C80: MISCELLANEOUS | H80: 69 | I80: 5 | J80: B | K80: 8
B81: 9075 | C81: Prior Year Expenditure Adjustment | H81: 69 | I81: 5 | J81: B | K81: 8 | M81: 77 | N81: 6 | O81: C | P81: 4
C84: Other Operating Expenses Not Reported Above
C85: OPERATING EXPENSES - 2 SUB-TOTAL: | D85: =SUM(D30:D84) -> 0 | E85: =SUM(E30:E84) -> 0 | F85: =SUM(F30:F84) -> 0
A86: SUPPLIES AND MATERIALS - 3 | M86: 77 | N86: 6 | O86: C | P86: 4
A87: 0100 | C87: SUPPLIES | M87: 77 | N87: 6 | O87: C | P87: 4
B88: 0101 | C88: Office | H88: 70 | I88: 5 | J88: B | K88: 9
B89: 0102 | C89: Chemical | H89: 70 | I89: 5 | J89: B | K89: 9
B90: 0103 | C90: Janitorial | H90: 70 | I90: 5 | J90: B | K90: 9
B91: 0104 | C91: Building and Grounds Supplies | H91: 70 | I91: 5 | J91: B | K91: 9
B92: 0105 | C92: Medical | H92: 70 | I92: 5 | J92: B | K92: 9
B93: 0106 | C93: Shop Supplies | H93: 70 | I93: 5 | J93: B | K93: 9
B94: 0107 | C94: Building Supplies | H94: 70 | I94: 5 | J94: B | K94: 9
B95: 0109 | C95: Shop Tools | H95: 70 | I95: 5 | J95: B | K95: 9
B96: 0110 | C96: Small Tools, etc. | H96: 70 | I96: 5 | J96: B | K96: 9
B97: 0126 | C97: Road Supplies | H97: 70 | I97: 5 | J97: B | K97: 9
C100: Other Supplies Expenses Not Reported Above
A101: 0200 | C101: MATERIALS | H101: 70 | I101: 5 | J101: B | K101: 9 | M101: 77 | N101: 6 | O101: C | P101: 4
B102: 0201 | C102: Asphaltic | H102: 70 | I102: 5 | J102: B | K102: 9
B103: 0202 | C103: Gravel and Borrow | H103: 70 | I103: 5 | J103: B | K103: 9
B104: 0203 | C104: Grader Blades | H104: 70 | I104: 5 | J104: B | K104: 9
B105: 0204 | C105: Fences, etc. | H105: 70 | I105: 5 | J105: B | K105: 9
B106: 0205 | C106: Concrete, etc. | H106: 70 | I106: 5 | J106: B | K106: 9
...
